"dora_reachy1/__init__,py"
dora_reachy1/main.py
dora_reachy1-0.3.6.dist-info/METADATA
dora_reachy1-0.3.6.dist-info/WHEEL
dora_reachy1-0.3.6.dist-info/entry_points.txt
dora_reachy1-0.3.6.dist-info/RECORD
